bohrium_api-0.11.0.post60.dist-info/top_level.txt
bohrium_api-0.11.0.post60.dist-info/RECORD
bohrium_api-0.11.0.post60.dist-info/METADATA
bohrium_api-0.11.0.post60.dist-info/WHEEL
bohrium_api.libs/libatlas-b6fb69b0.so.3.0
bohrium_api.libs/libf77blas-75a5c7e0.so.3.0
bohrium_api.libs/libOpenCL-03c0bd12.so.1
bohrium_api.libs/libbh-19c00be9.so
bohrium_api.libs/liblapack-7aef6c42.so.3.0
bohrium_api.libs/libgfortran-139be63a.so.3.0.0
bohrium_api.libs/libcudart-0630a1aa.so.8.0.44
bohrium_api.libs/libcblas-70dd3697.so.3.0
bohrium_api.libs/libbhxx-654b4109.so
bohrium_api.libs/libsigsegv-b61109d7.so.2.0.3
bohrium_api.libs/libbhc-e27406dc.so
bohrium_api/_bh_api.cpython-37m-x86_64-linux-gnu.so
bohrium_api/config.ini
bohrium_api/stack_info.py
bohrium_api/__main__.py
bohrium_api/_info.py
bohrium_api/messaging.py
bohrium_api/version.py
bohrium_api/__init__.py
bohrium_api/.libs/libbh_lapack_ele.so
bohrium_api/.libs/libbh_ve_cuda.so
bohrium_api/.libs/libbh_ve_openmp.so
bohrium_api/.libs/libbh_ve_opencl.so
bohrium_api/.libs/libbh_opencv_filtering.so
bohrium_api/.libs/libbh_filter_bcexp.so
bohrium_api/.libs/libbh_lapack_sesvp.so
bohrium_api/.libs/libbh_filter_bccon.so
bohrium_api/.libs/libbh_lapack_egsep.so
bohrium_api/.libs/libbh_lapack_gesvp.so
bohrium_api/.libs/libbh_vem_node.so
bohrium_api/.libs/libbh_lapack_le.so
bohrium_api/.libs/libbh_filter_pprint.so
bohrium_api/.libs/libbh_lapack_elsp.so
bohrium_api/.libs/libbh_lapack_lsp.so
bohrium_api/.libs/libbh_lapack_egnep.so
bohrium_api/.libs/libbh_filter_noneremover.so
bohrium_api/.libs/libbh_blas.so
bohrium_api/.libs/libbh_opencv_threshold.so
bohrium_api/include/bohrium_api.h
bohrium_api/include/Random123/aes.h
bohrium_api/include/Random123/ars.h
bohrium_api/include/Random123/threefry.h
bohrium_api/include/Random123/array.h
bohrium_api/include/Random123/philox.h
bohrium_api/include/Random123/ReinterpretCtr.hpp
bohrium_api/include/Random123/MicroURNG.hpp
bohrium_api/include/Random123/gsl_microrng.h
bohrium_api/include/Random123/features/clangfeatures.h
bohrium_api/include/Random123/features/pgccfeatures.h
bohrium_api/include/Random123/features/xlcfeatures.h
