Metadata-Version: 2.1
Name: bohrium-api
Version: 0.11.0.post60
Summary: Bohrium Python API
Home-page: http://bh107.org
Author: The Bohrium Team
Author-email: contact@bh107.org
Maintainer: Mads R. B. Kristensen
Maintainer-email: madsbk@gmail.com
License: GPL
Keywords: Bohrium,bh107,Python,C,HPC,MPI,PGAS,CUDA,OpenCL,OpenMP
Platform: Linux
Platform: OSX
Classifier: Development Status :: 4 - Beta
Classifier: Intended Audience :: Developers
Classifier: Intended Audience :: Science/Research
Classifier: Topic :: Scientific/Engineering
Classifier: Topic :: Software Development
Classifier: License :: OSI Approved :: GNU General Public License (GPL)
Classifier: Programming Language :: Python :: 2.7
Classifier: Programming Language :: Python :: 3
Classifier: Programming Language :: C
